{"legislative_session": "2025", "identifier": "SB00009", "title": "AN ACT CONCERNING THE ENVIRONMENT, CLIMATE AND SUSTAINABLE MUNICIPAL AND STATE PLANNING, AND THE USE OF NEONICOTINOIDS AND SECOND-GENERATION ANTICOAGULANT RODENTICIDES.", "from_organization": "~{\"classification\": \"upper\"}", "classification": ["bill"], "subject": ["Affordable housing", "Assessments", "Bridges", "Civil preparedness", "Climate change", "Coastal management", "Consumer Protection Department", "Development rights", "Disclosure", "Districts", "Drinking water", "Electronic government information", "Emergency Services and Public Protection, Department of", "Energy and Environmental Protection, Department of", "Evacuation", "Fair housing choice", "Fines (Penalties)", "Flood insurance", "Geospatial informations systems", "Hazard mitigation and floodplain management", "Highway construction", "Housing development", "Infrastructure", "Interlocal agreements", "Invasive species", "Landlord and tenant", "Leases", "Municipal bonds", "Municipal plans of conservation and development", "Municipalities", "New home warranties", "Ordinances", "Personal risk insurance", "Pesticides", "Planning and zoning commissions", "Plans", "Policy and Management, Office of", "Property tax assessments", "Real estate", "Regional councils of governments", "Rent", "Reports", "Rodents", "Sales", "Sewage treatment facilities", "State funds", "State mandates to municipalities", "Subsurface sewage disposal systems", "Tax incremental financing", "Town aid grants for highways and bridges", "Transportation Department", "Violations", "Water Planning Council", "Water supply", "Zoning"], "abstracts": [], "other_titles": [], "other_identifiers": [], "actions": [{"description": "REF. TO JOINT COMM. ON Environment", "date": "2025-01-08", "organization_id": "~{\"classification\": \"upper\"}", "classification": ["referral-committee"], "related_entities": []}, {"description": "Vote to Draft", "date": "2025-02-10", "organization_id": "~{\"classification\": \"upper\"}", "classification": [], "related_entities": []}, {"description": "DRAFTED BY COMMITTEE", "date": "2025-02-21", "organization_id": "~{\"classification\": \"upper\"}", "classification": [], "related_entities": []}, {"description": "REF. TO JOINT COMM. ON Environment", "date": "2025-02-24", "organization_id": "~{\"classification\": \"upper\"}", "classification": ["referral-committee"], "related_entities": []}, {"description": "PUBLIC HEARING 0303", "date": "2025-02-25", "organization_id": "~{\"classification\": \"upper\"}", "classification": [], "related_entities": []}, {"description": "Joint Favorable Substitute", "date": "2025-03-14", "organization_id": "~{\"classification\": \"upper\"}", "classification": ["committee-passage-favorable"], "related_entities": []}, {"description": "FILED WITH LCO", "date": "2025-03-17", "organization_id": "~{\"classification\": \"upper\"}", "classification": ["filing"], "related_entities": []}, {"description": "REFERRED TO Office of Legislative Research AND Office of Fiscal Analysis 04/01/25", "date": "2025-03-27", "organization_id": "~{\"classification\": \"upper\"}", "classification": ["referral"], "related_entities": []}, {"description": "RPTD. OUT OF LCO", "date": "2025-04-02", "organization_id": "~{\"classification\": \"upper\"}", "classification": [], "related_entities": []}, {"description": "FAV. RPT., TAB. FOR CAL., SEN.", "date": "2025-04-02", "organization_id": "~{\"classification\": \"upper\"}", "classification": ["reading-2"], "related_entities": []}, {"description": "SENATE CALENDAR NUMBER 240", "date": "2025-04-02", "organization_id": "~{\"classification\": \"upper\"}", "classification": [], "related_entities": []}, {"description": "FILE NO. 418", "date": "2025-04-02", "organization_id": "~{\"classification\": \"upper\"}", "classification": [], "related_entities": []}, {"description": "REF. BY SEN. TO COMM. ON Judiciary", "date": "2025-04-23", "organization_id": "~{\"classification\": \"upper\"}", "classification": [], "related_entities": []}, {"description": "Joint Favorable", "date": "2025-04-25", "organization_id": "~{\"classification\": \"upper\"}", "classification": ["committee-passage-favorable"], "related_entities": []}, {"description": "FILED WITH LCO", "date": "2025-04-28", "organization_id": "~{\"classification\": \"upper\"}", "classification": ["filing"], "related_entities": []}, {"description": "RPTD. OUT OF LCO", "date": "2025-04-28", "organization_id": "~{\"classification\": \"upper\"}", "classification": [], "related_entities": []}, {"description": "NO NEW FILE BY COMM. ON Judiciary", "date": "2025-04-28", "organization_id": "~{\"classification\": \"upper\"}", "classification": [], "related_entities": []}, {"description": "FAV. RPT., TAB. FOR CAL., SEN.", "date": "2025-04-28", "organization_id": "~{\"classification\": \"upper\"}", "classification": ["reading-2"], "related_entities": []}, {"description": "REF. BY SEN. TO COMM. ON Appropriations", "date": "2025-05-01", "organization_id": "~{\"classification\": \"upper\"}", "classification": [], "related_entities": []}, {"description": "Joint Favorable", "date": "2025-05-05", "organization_id": "~{\"classification\": \"upper\"}", "classification": ["committee-passage-favorable"], "related_entities": []}, {"description": "FILED WITH LCO", "date": "2025-05-06", "organization_id": "~{\"classification\": \"upper\"}", "classification": ["filing"], "related_entities": []}, {"description": "RPTD. OUT OF LCO", "date": "2025-05-07", "organization_id": "~{\"classification\": \"upper\"}", "classification": [], "related_entities": []}, {"description": "NO NEW FILE BY COMM. ON Appropriations", "date": "2025-05-07", "organization_id": "~{\"classification\": \"upper\"}", "classification": [], "related_entities": []}, {"description": "FAV. RPT., TAB. FOR CAL., SEN.", "date": "2025-05-07", "organization_id": "~{\"classification\": \"upper\"}", "classification": ["reading-2"], "related_entities": []}, {"description": "REF. BY SEN. TO COMM. ON Finance, Revenue and Bonding", "date": "2025-05-08", "organization_id": "~{\"classification\": \"upper\"}", "classification": [], "related_entities": []}, {"description": "IMMEDIATE TRANSMITTAL TO COMMITTEE", "date": "2025-05-08", "organization_id": "~{\"classification\": \"upper\"}", "classification": [], "related_entities": []}, {"description": "Joint Favorable", "date": "2025-05-12", "organization_id": "~{\"classification\": \"upper\"}", "classification": ["committee-passage-favorable"], "related_entities": []}, {"description": "FILED WITH LCO", "date": "2025-05-12", "organization_id": "~{\"classification\": \"upper\"}", "classification": ["filing"], "related_entities": []}, {"description": "RPTD. OUT OF LCO", "date": "2025-05-12", "organization_id": "~{\"classification\": \"upper\"}", "classification": [], "related_entities": []}, {"description": "NO NEW FILE BY COMM. ON Finance, Revenue and Bonding", "date": "2025-05-13", "organization_id": "~{\"classification\": \"upper\"}", "classification": [], "related_entities": []}, {"description": "FAV. RPT., TAB. FOR CAL., SEN.", "date": "2025-05-13", "organization_id": "~{\"classification\": \"upper\"}", "classification": ["reading-2"], "related_entities": []}, {"description": "SEN. ADOPTED  SEN. AMEND. SCH. A", "date": "2025-05-15", "organization_id": "~{\"classification\": \"upper\"}", "classification": ["amendment-passage"], "related_entities": []}, {"description": "SEN. PASSED, SEN. AMEND. SCH. A", "date": "2025-05-15", "organization_id": "~{\"classification\": \"upper\"}", "classification": ["passage"], "related_entities": []}, {"description": "FAV. RPT., TABLED FOR HOUSE CALENDAR", "date": "2025-05-16", "organization_id": "~{\"classification\": \"lower\"}", "classification": ["reading-2"], "related_entities": []}, {"description": "HOUSE CALENDAR NUMBER 613", "date": "2025-05-16", "organization_id": "~{\"classification\": \"lower\"}", "classification": [], "related_entities": []}, {"description": "HOUSE ADOPTED SEN. AMEND. SCH. A", "date": "2025-05-28", "organization_id": "~{\"classification\": \"lower\"}", "classification": ["amendment-passage"], "related_entities": []}, {"description": "HOUSE PASSED, SEN. AMEND. SCH. A", "date": "2025-05-28", "organization_id": "~{\"classification\": \"lower\"}", "classification": ["passage"], "related_entities": []}, {"description": "IN CONCURRENCE", "date": "2025-05-28", "organization_id": "~{\"classification\": \"upper\"}", "classification": [], "related_entities": []}, {"description": "PUBLIC ACT 25-33", "date": "2025-06-03", "organization_id": "~{\"classification\": \"upper\"}", "classification": [], "related_entities": []}, {"description": "TRANSMITTED TO SECRETARY OF THE STATE", "date": "2025-06-05", "organization_id": "~{\"classification\": \"upper\"}", "classification": [], "related_entities": []}, {"description": "TRANSMITTED BY SECRETARY OF THE STATE TO GOVERNOR", "date": "2025-06-09", "organization_id": "~{\"classification\": \"upper\"}", "classification": ["executive-receipt"], "related_entities": []}, {"description": "SIGNED BY GOVERNOR", "date": "2025-06-10", "organization_id": "~{\"classification\": \"upper\"}", "classification": ["executive-signature"], "related_entities": []}], "sponsorships": [{"name": "Martin M. Looney", "classification": "primary", "entity_type": "person", "primary": true, "person_id": "~{\"name\": \"Martin M. Looney\"}", "organization_id": null}, {"name": "Bob Duff", "classification": "primary", "entity_type": "person", "primary": true, "person_id": "~{\"name\": \"Bob Duff\"}", "organization_id": null}, {"name": "Saud Anwar", "classification": "primary", "entity_type": "person", "primary": true, "person_id": "~{\"name\": \"Saud Anwar\"}", "organization_id": null}, {"name": "Jorge Cabrera", "classification": "primary", "entity_type": "person", "primary": true, "person_id": "~{\"name\": \"Jorge Cabrera\"}", "organization_id": null}, {"name": "Christine Cohen", "classification": "primary", "entity_type": "person", "primary": true, "person_id": "~{\"name\": \"Christine Cohen\"}", "organization_id": null}, {"name": "Mae Flexer", "classification": "primary", "entity_type": "person", "primary": true, "person_id": "~{\"name\": \"Mae Flexer\"}", "organization_id": null}, {"name": "Sujata Gadkar-wilcox", "classification": "primary", "entity_type": "person", "primary": true, "person_id": "~{\"name\": \"Sujata Gadkar-wilcox\"}", "organization_id": null}, {"name": "Herron Gaston", "classification": "primary", "entity_type": "person", "primary": true, "person_id": "~{\"name\": \"Herron Gaston\"}", "organization_id": null}, {"name": "Jan Hochadel", "classification": "primary", "entity_type": "person", "primary": true, "person_id": "~{\"name\": \"Jan Hochadel\"}", "organization_id": null}, {"name": "Paul Honig", "classification": "primary", "entity_type": "person", "primary": true, "person_id": "~{\"name\": \"Paul Honig\"}", "organization_id": null}, {"name": "Julie Kushner", "classification": "primary", "entity_type": "person", "primary": true, "person_id": "~{\"name\": \"Julie Kushner\"}", "organization_id": null}, {"name": "Matthew L. Lesser", "classification": "primary", "entity_type": "person", "primary": true, "person_id": "~{\"name\": \"Matthew L. Lesser\"}", "organization_id": null}, {"name": "Rick Lopes", "classification": "primary", "entity_type": "person", "primary": true, "person_id": "~{\"name\": \"Rick Lopes\"}", "organization_id": null}, {"name": "Ceci Maher", "classification": "primary", "entity_type": "person", "primary": true, "person_id": "~{\"name\": \"Ceci Maher\"}", "organization_id": null}, {"name": "James J. Maroney", "classification": "primary", "entity_type": "person", "primary": true, "person_id": "~{\"name\": \"James J. Maroney\"}", "organization_id": null}, {"name": "Martha Marx", "classification": "primary", "entity_type": "person", "primary": true, "person_id": "~{\"name\": \"Martha Marx\"}", "organization_id": null}, {"name": "Douglas Mccrory", "classification": "primary", "entity_type": "person", "primary": true, "person_id": "~{\"name\": \"Douglas Mccrory\"}", "organization_id": null}, {"name": "Patricia Billie Miller", "classification": "primary", "entity_type": "person", "primary": true, "person_id": "~{\"name\": \"Patricia Billie Miller\"}", "organization_id": null}, {"name": "Norman Needleman", "classification": "primary", "entity_type": "person", "primary": true, "person_id": "~{\"name\": \"Norman Needleman\"}", "organization_id": null}, {"name": "Md Rahman", "classification": "primary", "entity_type": "person", "primary": true, "person_id": "~{\"name\": \"Md Rahman\"}", "organization_id": null}, {"name": "Derek Slap", "classification": "primary", "entity_type": "person", "primary": true, "person_id": "~{\"name\": \"Derek Slap\"}", "organization_id": null}, {"name": "Gary A. Winfield", "classification": "primary", "entity_type": "person", "primary": true, "person_id": "~{\"name\": \"Gary A. Winfield\"}", "organization_id": null}, {"name": "Michael \"mj\" Shannon", "classification": "primary", "entity_type": "person", "primary": true, "person_id": "~{\"name\": \"Michael \\\"mj\\\" Shannon\"}", "organization_id": null}, {"name": "Aundre Bumgardner", "classification": "primary", "entity_type": "person", "primary": true, "person_id": "~{\"name\": \"Aundre Bumgardner\"}", "organization_id": null}, {"name": "Jonathan Jacobson", "classification": "primary", "entity_type": "person", "primary": true, "person_id": "~{\"name\": \"Jonathan Jacobson\"}", "organization_id": null}, {"name": "Brandon Chafee", "classification": "primary", "entity_type": "person", "primary": true, "person_id": "~{\"name\": \"Brandon Chafee\"}", "organization_id": null}, {"name": "Sarah Keitt", "classification": "primary", "entity_type": "person", "primary": true, "person_id": "~{\"name\": \"Sarah Keitt\"}", "organization_id": null}, {"name": "Anne M. Hughes", "classification": "primary", "entity_type": "person", "primary": true, "person_id": "~{\"name\": \"Anne M. Hughes\"}", "organization_id": null}, {"name": "Patricia A. Dillon", "classification": "primary", "entity_type": "person", "primary": true, "person_id": "~{\"name\": \"Patricia A. Dillon\"}", "organization_id": null}, {"name": "Jane M. Garibay", "classification": "primary", "entity_type": "person", "primary": true, "person_id": "~{\"name\": \"Jane M. Garibay\"}", "organization_id": null}, {"name": "John-michael Parker", "classification": "primary", "entity_type": "person", "primary": true, "person_id": "~{\"name\": \"John-michael Parker\"}", "organization_id": null}, {"name": "Amy Morrin Bello", "classification": "primary", "entity_type": "person", "primary": true, "person_id": "~{\"name\": \"Amy Morrin Bello\"}", "organization_id": null}, {"name": "Kevin Ryan", "classification": "primary", "entity_type": "person", "primary": true, "person_id": "~{\"name\": \"Kevin Ryan\"}", "organization_id": null}, {"name": "Frank Smith", "classification": "primary", "entity_type": "person", "primary": true, "person_id": "~{\"name\": \"Frank Smith\"}", "organization_id": null}, {"name": "Tammy R. Exum", "classification": "primary", "entity_type": "person", "primary": true, "person_id": "~{\"name\": \"Tammy R. Exum\"}", "organization_id": null}, {"name": "Kerry S. Wood", "classification": "primary", "entity_type": "person", "primary": true, "person_id": "~{\"name\": \"Kerry S. Wood\"}", "organization_id": null}, {"name": "Hector Arzeno", "classification": "primary", "entity_type": "person", "primary": true, "person_id": "~{\"name\": \"Hector Arzeno\"}", "organization_id": null}, {"name": "Robin E. Comey", "classification": "primary", "entity_type": "person", "primary": true, "person_id": "~{\"name\": \"Robin E. Comey\"}", "organization_id": null}, {"name": "James Sanchez", "classification": "primary", "entity_type": "person", "primary": true, "person_id": "~{\"name\": \"James Sanchez\"}", "organization_id": null}, {"name": "Tom Delnicki", "classification": "primary", "entity_type": "person", "primary": true, "person_id": "~{\"name\": \"Tom Delnicki\"}", "organization_id": null}, {"name": "Travis Simms", "classification": "primary", "entity_type": "person", "primary": true, "person_id": "~{\"name\": \"Travis Simms\"}", "organization_id": null}, {"name": "Laurie Sweet", "classification": "primary", "entity_type": "person", "primary": true, "person_id": "~{\"name\": \"Laurie Sweet\"}", "organization_id": null}, {"name": "Nick Gauthier", "classification": "primary", "entity_type": "person", "primary": true, "person_id": "~{\"name\": \"Nick Gauthier\"}", "organization_id": null}, {"name": "Eleni Kavros Degraw", "classification": "primary", "entity_type": "person", "primary": true, "person_id": "~{\"name\": \"Eleni Kavros Degraw\"}", "organization_id": null}, {"name": "Hubert D. Delany", "classification": "primary", "entity_type": "person", "primary": true, "person_id": "~{\"name\": \"Hubert D. Delany\"}", "organization_id": null}, {"name": "Eilish Collins Main", "classification": "primary", "entity_type": "person", "primary": true, "person_id": "~{\"name\": \"Eilish Collins Main\"}", "organization_id": null}, {"name": "Kenneth Gucker", "classification": "primary", "entity_type": "person", "primary": true, "person_id": "~{\"name\": \"Kenneth Gucker\"}", "organization_id": null}], "related_bills": [], "versions": [{"note": "Public Act No. 25-33", "links": [{"url": "https://www.cga.ct.gov/2025/ACT/PA/PDF/2025PA-00033-R00SB-00009-PA.PDF", "media_type": "application/pdf"}], "date": "", "classification": ""}, {"note": "FIN Joint Favorable", "links": [{"url": "https://www.cga.ct.gov/2025/TOB/S/PDF/2025SB-00009-R05-SB.PDF", "media_type": "application/pdf"}], "date": "", "classification": ""}, {"note": "APP Joint Favorable", "links": [{"url": "https://www.cga.ct.gov/2025/TOB/S/PDF/2025SB-00009-R04-SB.PDF", "media_type": "application/pdf"}], "date": "", "classification": ""}, {"note": "JUD Joint Favorable", "links": [{"url": "https://www.cga.ct.gov/2025/TOB/S/PDF/2025SB-00009-R03-SB.PDF", "media_type": "application/pdf"}], "date": "", "classification": ""}, {"note": "File No. 418", "links": [{"url": "https://www.cga.ct.gov/2025/FC/PDF/2025SB-00009-R000418-FC.PDF", "media_type": "application/pdf"}], "date": "", "classification": ""}, {"note": "ENV Joint Favorable Substitute", "links": [{"url": "https://www.cga.ct.gov/2025/TOB/S/PDF/2025SB-00009-R02-SB.PDF", "media_type": "application/pdf"}], "date": "", "classification": ""}, {"note": "Committee Bill", "links": [{"url": "https://www.cga.ct.gov/2025/TOB/S/PDF/2025SB-00009-R01-SB.PDF", "media_type": "application/pdf"}], "date": "", "classification": ""}, {"note": "Proposed Bill", "links": [{"url": "https://www.cga.ct.gov/2025/TOB/S/PDF/2025SB-00009-R00-SB.PDF", "media_type": "application/pdf"}], "date": "", "classification": ""}], "documents": [{"note": "Fiscal Note for SB-9, As Amended by Senate \"A\" (LCO 8466)", "links": [{"url": "https://www.cga.ct.gov/2025/FN/PDF/2025SB-00009-R01-FN.PDF", "media_type": ""}], "date": "", "classification": ""}, {"note": "Fiscal Note For File Copy 418", "links": [{"url": "https://www.cga.ct.gov/2025/FN/PDF/2025SB-00009-R000418-FN.PDF", "media_type": ""}], "date": "", "classification": ""}, {"note": "Bill Analysis for SB-9, as amended by Senate \"A\"", "links": [{"url": "https://www.cga.ct.gov/2025/BA/PDF/2025SB-00009-R01-BA.PDF", "media_type": ""}], "date": "", "classification": ""}, {"note": "Bill Analysis For File Copy 418", "links": [{"url": "https://www.cga.ct.gov/2025/BA/PDF/2025SB-00009-R000418-BA.PDF", "media_type": ""}], "date": "", "classification": ""}], "citations": [], "sources": [{"url": "ftp://ftp.cga.ct.gov/pub/data/bill_info.csv", "note": ""}, {"url": "https://www.cga.ct.gov/asp/cgabillstatus/cgabillstatus.asp?selBillType=Bill&bill_num=SB9&which_year=2025", "note": ""}], "extras": {}, "jurisdiction": {"id": "ocd-jurisdiction/country:us/state:ct/government", "name": "Connecticut", "classification": "state", "division_id": "ocd-division/country:us/state:ct"}, "scraped_at": "2026-01-12T08:18:32+00:00", "_id": "485c0a94-ef8f-11f0-adce-da1dab029dfb"}