{"legislative_session": "2025", "identifier": "SR00051", "title": "RESOLUTION CONCERNING THE RULES OF THE SENATE FOR THE NOVEMBER SPECIAL SESSION, 2025.", "from_organization": "~{\"classification\": \"upper\"}", "classification": ["resolution"], "subject": ["General Assembly rules"], "abstracts": [], "other_titles": [], "other_identifiers": [], "actions": [{"description": "ADOPTED, SENATE", "date": "2025-11-12", "organization_id": "~{\"classification\": \"upper\"}", "classification": ["passage"], "related_entities": []}], "sponsorships": [{"name": "Martin M. Looney", "classification": "primary", "entity_type": "person", "primary": true, "person_id": "~{\"name\": \"Martin M. Looney\"}", "organization_id": null}, {"name": "Bob Duff", "classification": "primary", "entity_type": "person", "primary": true, "person_id": "~{\"name\": \"Bob Duff\"}", "organization_id": null}], "related_bills": [], "versions": [{"note": "Senate Resolution", "links": [{"url": "https://www.cga.ct.gov/2025/TOB/S/PDF/2025SR-00051-R00-SB.PDF", "media_type": "application/pdf"}], "date": "", "classification": ""}], "documents": [], "citations": [], "sources": [{"url": "ftp://ftp.cga.ct.gov/pub/data/bill_info.csv", "note": ""}, {"url": "https://www.cga.ct.gov/asp/cgabillstatus/cgabillstatus.asp?selBillType=Bill&bill_num=SR51&which_year=2025", "note": ""}], "extras": {}, "jurisdiction": {"id": "ocd-jurisdiction/country:us/state:ct/government", "name": "Connecticut", "classification": "state", "division_id": "ocd-division/country:us/state:ct"}, "scraped_at": "2025-12-25T08:16:10+00:00", "_id": "f87c38d8-e169-11f0-8d9b-eeb676c42ffd"}