{"legislative_session": "2025", "identifier": "SB00396", "title": "AN ACT CONCERNING THE ADMINISTRATION OF THE WRITTEN EXAMINATION FOR BUILDING INSPECTOR LICENSURE.", "from_organization": "~{\"classification\": \"upper\"}", "classification": ["bill"], "subject": ["Building inspectors and officials", "Occupational licenses", "Tests"], "abstracts": [], "other_titles": [], "other_identifiers": [], "actions": [{"description": "REF. TO JOINT COMM. ON Planning and Development", "date": "2025-01-09", "organization_id": "~{\"classification\": \"upper\"}", "classification": ["referral-committee"], "related_entities": []}, {"description": "Change of Reference GAE", "date": "2025-01-17", "organization_id": "~{\"classification\": \"upper\"}", "classification": [], "related_entities": []}, {"description": "CHG. REF., SEN. TO COMM. ON Government Administration and Elections", "date": "2025-01-22", "organization_id": "~{\"classification\": \"upper\"}", "classification": [], "related_entities": []}, {"description": "CHG. REF., HOUSE TO COMM. ON Government Administration and Elections", "date": "2025-01-22", "organization_id": "~{\"classification\": \"upper\"}", "classification": [], "related_entities": []}], "sponsorships": [{"name": "Jeff Gordon", "classification": "primary", "entity_type": "person", "primary": true, "person_id": "~{\"name\": \"Jeff Gordon\"}", "organization_id": null}], "related_bills": [], "versions": [{"note": "Proposed Bill", "links": [{"url": "https://www.cga.ct.gov/2025/TOB/S/PDF/2025SB-00396-R00-SB.PDF", "media_type": "application/pdf"}], "date": "", "classification": ""}], "documents": [], "citations": [], "sources": [{"url": "ftp://ftp.cga.ct.gov/pub/data/bill_info.csv", "note": ""}, {"url": "https://www.cga.ct.gov/asp/cgabillstatus/cgabillstatus.asp?selBillType=Bill&bill_num=SB396&which_year=2025", "note": ""}], "extras": {}, "jurisdiction": {"id": "ocd-jurisdiction/country:us/state:ct/government", "name": "Connecticut", "classification": "state", "division_id": "ocd-division/country:us/state:ct"}, "scraped_at": "2026-01-29T08:26:08+00:00", "_id": "29899d6a-fcec-11f0-aceb-d270f8dbfbdf"}