{"legislative_session": "2025", "identifier": "HB05927", "title": "AN ACT CONCERNING INCENTIVES FOR THE REPLACEMENT OF RESIDENTIAL ELECTRIC RESISTANCE HEATING SYSTEMS.", "from_organization": "~{\"classification\": \"lower\"}", "classification": ["bill"], "subject": ["Electricity", "Heating"], "abstracts": [], "other_titles": [], "other_identifiers": [], "actions": [{"description": "REF. TO JOINT COMM. ON Energy and Technology", "date": "2025-01-22", "organization_id": "~{\"classification\": \"lower\"}", "classification": ["referral-committee"], "related_entities": []}], "sponsorships": [{"name": "Steven Winter", "classification": "primary", "entity_type": "person", "primary": true, "person_id": "~{\"name\": \"Steven Winter\"}", "organization_id": null}, {"name": "Mary M. Mushinsky", "classification": "primary", "entity_type": "person", "primary": true, "person_id": "~{\"name\": \"Mary M. Mushinsky\"}", "organization_id": null}], "related_bills": [], "versions": [{"note": "Proposed Bill", "links": [{"url": "https://www.cga.ct.gov/2025/TOB/H/PDF/2025HB-05927-R00-HB.PDF", "media_type": "application/pdf"}], "date": "", "classification": ""}], "documents": [], "citations": [], "sources": [{"url": "ftp://ftp.cga.ct.gov/pub/data/bill_info.csv", "note": ""}, {"url": "https://www.cga.ct.gov/asp/cgabillstatus/cgabillstatus.asp?selBillType=Bill&bill_num=HB5927&which_year=2025", "note": ""}], "extras": {}, "jurisdiction": {"id": "ocd-jurisdiction/country:us/state:ct/government", "name": "Connecticut", "classification": "state", "division_id": "ocd-division/country:us/state:ct"}, "scraped_at": "2026-01-05T08:18:40+00:00", "_id": "2449a344-ea0f-11f0-85a6-f240f0ff9f8c"}