{"legislative_session": "2025", "identifier": "SB00757", "title": "AN ACT REQUIRING SELF-FUNDED MUNICIPALITIES IN THIS STATE TO PROVIDE HEALTH INSURANCE COVERAGE FOR BREAST CANCER SCREENINGS.", "from_organization": "~{\"classification\": \"upper\"}", "classification": ["bill"], "subject": ["Cancer", "Health insurance", "Municipalities"], "abstracts": [], "other_titles": [], "other_identifiers": [], "actions": [{"description": "REF. TO JOINT COMM. ON Insurance and Real Estate", "date": "2025-01-17", "organization_id": "~{\"classification\": \"upper\"}", "classification": ["referral-committee"], "related_entities": []}], "sponsorships": [{"name": "Saud Anwar", "classification": "primary", "entity_type": "person", "primary": true, "person_id": "~{\"name\": \"Saud Anwar\"}", "organization_id": null}, {"name": "Jan Hochadel", "classification": "primary", "entity_type": "person", "primary": true, "person_id": "~{\"name\": \"Jan Hochadel\"}", "organization_id": null}], "related_bills": [], "versions": [{"note": "Proposed Bill", "links": [{"url": "https://www.cga.ct.gov/2025/TOB/S/PDF/2025SB-00757-R00-SB.PDF", "media_type": "application/pdf"}], "date": "", "classification": ""}], "documents": [], "citations": [], "sources": [{"url": "ftp://ftp.cga.ct.gov/pub/data/bill_info.csv", "note": ""}, {"url": "https://www.cga.ct.gov/asp/cgabillstatus/cgabillstatus.asp?selBillType=Bill&bill_num=SB757&which_year=2025", "note": ""}], "extras": {}, "jurisdiction": {"id": "ocd-jurisdiction/country:us/state:ct/government", "name": "Connecticut", "classification": "state", "division_id": "ocd-division/country:us/state:ct"}, "scraped_at": "2025-12-30T08:16:45+00:00", "_id": "e12a39d6-e557-11f0-9d4c-e6f5c9f46f42"}